[
    {
        "timestamp": "2022-12-19T03:45:07.973781",
        "distance": 24217,
        "duration": 3925,
        "duration_in_traffic": 3932
    },
    {
        "timestamp": "2022-12-19T12:59:41.803791",
        "distance": 23673,
        "duration": 3816,
        "duration_in_traffic": 4544
    },
    {
        "timestamp": "2022-12-20T03:45:53.031333",
        "distance": 23551,
        "duration": 3795,
        "duration_in_traffic": 4060
    },
    {
        "timestamp": "2022-12-20T12:59:42.358271",
        "distance": 26488,
        "duration": 4217,
        "duration_in_traffic": 4616
    },
    {
        "timestamp": "2022-12-21T03:45:16.409930",
        "distance": 24217,
        "duration": 3925,
        "duration_in_traffic": 4126
    },
    {
        "timestamp": "2022-12-21T12:50:32.184443",
        "distance": 25024,
        "duration": 3988,
        "duration_in_traffic": 5352
    },
    {
        "timestamp": "2022-12-22T03:43:39.225798",
        "distance": 23176,
        "duration": 3783,
        "duration_in_traffic": 3861
    },
    {
        "timestamp": "2022-12-22T12:50:30.991427",
        "distance": 23551,
        "duration": 3795,
        "duration_in_traffic": 4890
    },
    {
        "timestamp": "2022-12-23T03:43:44.547722",
        "distance": 23176,
        "duration": 3783,
        "duration_in_traffic": 3648
    },
    {
        "timestamp": "2022-12-23T12:49:46.167354",
        "distance": 25024,
        "duration": 3988,
        "duration_in_traffic": 5339
    },
    {
        "timestamp": "2022-12-24T03:43:39.645900",
        "distance": 23551,
        "duration": 3795,
        "duration_in_traffic": 3331
    },
    {
        "timestamp": "2022-12-24T12:48:55.519470",
        "distance": 24075,
        "duration": 3872,
        "duration_in_traffic": 4839
    },
    {
        "timestamp": "2022-12-25T03:43:41.939475",
        "distance": 23551,
        "duration": 3795,
        "duration_in_traffic": 3004
    },
    {
        "timestamp": "2022-12-25T12:49:07.562755",
        "distance": 24075,
        "duration": 3872,
        "duration_in_traffic": 4269
    },
    {
        "timestamp": "2022-12-26T03:43:42.106065",
        "distance": 23551,
        "duration": 3795,
        "duration_in_traffic": 3766
    },
    {
        "timestamp": "2022-12-26T12:49:35.413063",
        "distance": 24120,
        "duration": 3872,
        "duration_in_traffic": 4539
    }
]